yml2cli/__init__.py
yml2cli/yml2cli.py
yml2cli-0.2.1.dist-info/LICENSE
yml2cli-0.2.1.dist-info/METADATA
yml2cli-0.2.1.dist-info/WHEEL
yml2cli-0.2.1.dist-info/entry_points.txt
yml2cli-0.2.1.dist-info/top_level.txt
yml2cli-0.2.1.dist-info/RECORD
