Metadata-Version: 2.1
Name: yml2cli
Version: 0.2.1
Summary: Yaml to cli params converter
Home-page: https://github.com/krishnamiriyala/yml2cli
Author: Krishna Miriyala
Author-email: krishnambm@gmail.com
License: AS IS
License-File: LICENSE
Requires-Dist: pyyaml
